hatch_calver/__init__.py
hatch_calver/bump.py
hatch_calver/calver_scheme.py
hatch_calver/hatch_hooks.py
hatch_calver-2024.9.26.dist-info/METADATA
hatch_calver-2024.9.26.dist-info/WHEEL
hatch_calver-2024.9.26.dist-info/entry_points.txt
hatch_calver-2024.9.26.dist-info/licenses/LICENSE
hatch_calver-2024.9.26.dist-info/RECORD
